drf_dynamic_fields/__init__.py
drf_dynamic_fields-0.4.0.dist-info/LICENSE
drf_dynamic_fields-0.4.0.dist-info/METADATA
drf_dynamic_fields-0.4.0.dist-info/WHEEL
drf_dynamic_fields-0.4.0.dist-info/top_level.txt
drf_dynamic_fields-0.4.0.dist-info/zip-safe
drf_dynamic_fields-0.4.0.dist-info/RECORD
