Metadata-Version: 2.1
Name: drf_dynamic_fields
Version: 0.4.0
Summary: Dynamically return subset of Django REST Framework serializer fields
Home-page: https://github.com/dbrgn/drf-dynamic-fields
Author: Danilo Bargen
Author-email: mail@dbrgn.ch
License: MIT
Keywords: drf restframework rest_framework django_rest_framework serializers
Platform: UNKNOWN
Classifier: Development Status :: 5 - Production/Stable
Classifier: License :: OSI Approved :: MIT License
Classifier: Programming Language :: Python :: 3
Classifier: Framework :: Django
Classifier: Environment :: Web Environment
License-File: LICENSE
